odoo8_addon_website_event_excerpt_img-8.0.1.1.0-py2.7-nspkg.pth
odoo8_addon_website_event_excerpt_img-8.0.1.1.0.dist-info/top_level.txt
odoo8_addon_website_event_excerpt_img-8.0.1.1.0.dist-info/WHEEL
odoo8_addon_website_event_excerpt_img-8.0.1.1.0.dist-info/RECORD
odoo8_addon_website_event_excerpt_img-8.0.1.1.0.dist-info/metadata.json
odoo8_addon_website_event_excerpt_img-8.0.1.1.0.dist-info/DESCRIPTION.rst
odoo8_addon_website_event_excerpt_img-8.0.1.1.0.dist-info/METADATA
odoo8_addon_website_event_excerpt_img-8.0.1.1.0.dist-info/namespace_packages.txt
odoo_addons/website_event_excerpt_img/__openerp__.py
odoo_addons/website_event_excerpt_img/__init__.py
odoo_addons/website_event_excerpt_img/README.rst
odoo_addons/website_event_excerpt_img/models/__init__.py
odoo_addons/website_event_excerpt_img/models/event.py
odoo_addons/website_event_excerpt_img/i18n/es.po
odoo_addons/website_event_excerpt_img/views/event_event_view.xml
odoo_addons/website_event_excerpt_img/views/assets.xml
odoo_addons/website_event_excerpt_img/views/event.xml
odoo_addons/website_event_excerpt_img/images/backend.png
odoo_addons/website_event_excerpt_img/images/frontend.png
odoo_addons/website_event_excerpt_img/images/customize.png
odoo_addons/website_event_excerpt_img/static/description/icon.png
odoo_addons/website_event_excerpt_img/static/src/css/website_event_excerpt_img.css
odoo_addons/website_event_excerpt_img/static/src/css/website_event_excerpt_img.sass
odoo_addons/website_event_excerpt_img/static/src/css/website_event_excerpt_img.css.map
