Metadata-Version: 2.0
Name: odoo8-addon-website-event-excerpt-img
Version: 8.0.1.1.0
Summary: New layout for event summary, including an excerpt and image
Home-page: https://www.tecnativa.com
Author: UNKNOWN
Author-email: UNKNOWN
License: AGPL-3
Platform: UNKNOWN
Requires-Dist: odoo (<9.0a,>=8.0a)
Requires-Dist: odoo8-addon-html-image-url-extractor
Requires-Dist: odoo8-addon-html-text
Classifier: Programming Language :: Python :: 2.7
Classifier: Framework :: Odoo
Classifier: License :: OSI Approved :: GNU Affero General Public License v3
